{"trial_id": "36", "hyperparameters": {"space": [{"class_name": "Choice", "config": {"name": "activation", "default": "relu", "conditions": [], "values": ["relu", "tanh"], "ordered": false}}, {"class_name": "Boolean", "config": {"name": "dropout", "default": false, "conditions": []}}, {"class_name": "Int", "config": {"name": "units_0", "default": null, "conditions": [], "min_value": 20, "max_value": 500, "step": 20, "sampling": "linear"}}, {"class_name": "Int", "config": {"name": "units_1", "default": null, "conditions": [], "min_value": 20, "max_value": 500, "step": 20, "sampling": "linear"}}, {"class_name": "Int", "config": {"name": "units_2", "default": null, "conditions": [], "min_value": 20, "max_value": 500, "step": 20, "sampling": "linear"}}, {"class_name": "Choice", "config": {"name": "optimizer", "default": "sgd", "conditions": [], "values": ["sgd", "adam"], "ordered": false}}, {"class_name": "Float", "config": {"name": "lr", "default": 0.0001, "conditions": [], "min_value": 0.0001, "max_value": 0.1, "step": null, "sampling": "log"}}], "values": {"activation": "tanh", "dropout": false, "units_0": 340, "units_1": 200, "units_2": 100, "optimizer": "sgd", "lr": 0.013885118645864265}}, "metrics": {"metrics": {"loss": {"direction": "min", "observations": [{"value": [0.26372700929641724], "step": 17}]}, "accuracy": {"direction": "max", "observations": [{"value": [0.9034814834594727], "step": 17}]}, "val_loss": {"direction": "min", "observations": [{"value": [0.3095749020576477], "step": 17}]}, "val_accuracy": {"direction": "max", "observations": [{"value": [0.8853333592414856], "step": 17}]}}}, "score": 0.8853333592414856, "best_step": 17, "status": "COMPLETED", "message": null}